datalad_hirni/__init__.py
datalad_hirni/version.py
datalad_hirni/commands/__init__.py
datalad_hirni/commands/dicom2spec.py
datalad_hirni/commands/import_dicoms.py
datalad_hirni/commands/source_spec.py
datalad_hirni/commands/spec2bids.py
datalad_hirni/commands/spec4anything.py
datalad_hirni/resources/dummy_executable.sh
datalad_hirni/resources/procedures/cfg_hirni.py
datalad_hirni/resources/rules/custom_rules_template.py
datalad_hirni/resources/rules/test_rules.py
datalad_hirni/resources/rules/test_rules2.py
datalad_hirni/resources/rules/test_rules3.py
datalad_hirni/resources/webapp/index.html
datalad_hirni/resources/webapp/specedit.html
datalad_hirni/resources/webapp/studymetadata_edit.html
datalad_hirni/resources/webapp/css/bootstrap.min.css
datalad_hirni/resources/webapp/css/open-iconic-bootstrap.min.css
datalad_hirni/resources/webapp/css/specedit.css
datalad_hirni/resources/webapp/fonts/open-iconic.svg
datalad_hirni/resources/webapp/fonts/open-iconic.ttf
datalad_hirni/resources/webapp/fonts/open-iconic.woff
datalad_hirni/resources/webapp/js/axios.min.js
datalad_hirni/resources/webapp/js/bootstrap.bundle.min.js
datalad_hirni/resources/webapp/js/jquery.slim.min.js
datalad_hirni/resources/webapp/js/vue.min.js
datalad_hirni/support/BIDS_helper.py
datalad_hirni/support/__init__.py
datalad_hirni/support/default_rules.py
datalad_hirni/support/hirni_heuristic.py
datalad_hirni/support/spec_handler.py
datalad_hirni/support/spec_helpers.py
datalad_hirni/tests/__init__.py
datalad_hirni/tests/test_demos.py
datalad_hirni/tests/test_dicom2spec.py
datalad_hirni/tests/test_dicomconv.py
datalad_hirni/tests/test_import.py
datalad_hirni/tests/test_register.py
datalad_hirni/tests/test_spec.py
datalad_hirni/tests/test_spec_basic.py
datalad_hirni/tests/test_spec_rules.py
datalad_hirni/tests/utils.py
datalad_hirni/tests/resources/events2ev3.sh
datalad_hirni/tests/resources/ffa_design.fsf
datalad_hirni/tests/resources/fsl-simg-spec
datalad_hirni-0.0.8.dist-info/COPYING
datalad_hirni-0.0.8.dist-info/METADATA
datalad_hirni-0.0.8.dist-info/WHEEL
datalad_hirni-0.0.8.dist-info/entry_points.txt
datalad_hirni-0.0.8.dist-info/top_level.txt
datalad_hirni-0.0.8.dist-info/RECORD
