Metadata-Version: 2.1
Name: datalad-hirni
Version: 0.0.8
Summary: DataLad extension for raw data capturing and conversion workflows
Home-page: UNKNOWN
Author: DataLad developers
Author-email: team@datalad.org
License: UNKNOWN
Platform: UNKNOWN
Requires-Dist: datalad-container (>=1.1.2)
Requires-Dist: datalad-metalad (>=0.2.0)
Requires-Dist: datalad-neuroimaging (>=0.3.1)
Requires-Dist: datalad-webapp (>=0.3)
Requires-Dist: datalad[full] (>=0.14.0)
Provides-Extra: devel-docs
Requires-Dist: pypandoc ; extra == 'devel-docs'
Requires-Dist: sphinx-rtd-theme ; extra == 'devel-docs'
Requires-Dist: sphinx (>=1.6.2) ; extra == 'devel-docs'
